siri/__init__.py
siri/main.py
siri/siri_connection_monitoring_service.py
siri/siri_connection_timetable_service.py
siri/siri_discovery.py
siri/siri_estimated_timetable_service.py
siri/siri_facility_monitoring_service.py
siri/siri_general_message_service.py
siri/siri_production_timetable_service.py
siri/siri_situation_exchange_service.py
siri/siri_stop_monitoring_service.py
siri/siri_stop_timetable_service.py
siri/siri_vehicle_monitoring_service.py
siri/acsb/__init__.py
siri/acsb/acsb_accessibility_v0_3.py
siri/acsb/acsb_limitations_v0_2.py
siri/acsb/acsb_passenger_mobility_v0_3.py
siri/datex2/__init__.py
siri/datex2/datexiischema_2_0_rc1_2_0.py
siri/ifopt/__init__.py
siri/ifopt/ifopt_administration_v0_3.py
siri/ifopt/ifopt_checkpoint_v0_3.py
siri/ifopt/ifopt_countries_v0_2.py
siri/ifopt/ifopt_equipment_v0_3.py
siri/ifopt/ifopt_location_v0_3.py
siri/ifopt/ifopt_modes_v0_2.py
siri/ifopt/ifopt_modification_v0_3.py
siri/ifopt/ifopt_path_v0_2.py
siri/ifopt/ifopt_stop_v0_3.py
siri/ifopt/ifopt_time_v0_2.py
siri/ifopt/ifopt_types_v0_2.py
siri/siri/__init__.py
siri/siri/siri_common_services_v2_0.py
siri/siri/siri_request_error_conditions_v2_0.py
siri/siri/siri_request_support_v2_0.py
siri/siri/siri_requests_v2_0.py
siri/siri_model/__init__.py
siri/siri_model/siri_dated_vehicle_journey_v2_0.py
siri/siri_model/siri_estimated_vehicle_journey_v2_0.py
siri/siri_model/siri_facilities_v1_2.py
siri/siri_model/siri_facility_v2_0.py
siri/siri_model/siri_feature_support_v2_0.py
siri/siri_model/siri_interchange_journey_v2_0.py
siri/siri_model/siri_journey_support_v2_0.py
siri/siri_model/siri_journey_v2_0.py
siri/siri_model/siri_model_permissions_v2_0.py
siri/siri_model/siri_modes_v1_1.py
siri/siri_model/siri_monitored_vehicle_journey_v2_0.py
siri/siri_model/siri_reference_v2_0.py
siri/siri_model/siri_situation_actions_v1_0.py
siri/siri_model/siri_situation_affects_v2_0.py
siri/siri_model/siri_situation_classifiers_v1_1.py
siri/siri_model/siri_situation_identity_v1_1.py
siri-0.1.0.dist-info/LICENSE
siri-0.1.0.dist-info/METADATA
siri-0.1.0.dist-info/WHEEL
siri-0.1.0.dist-info/top_level.txt
siri-0.1.0.dist-info/RECORD
