Metadata-Version: 2.1
Name: siri
Version: 0.1.0
Summary: A library for dealing with Service Interface for Real-time Information (SIRI) data
Home-page: https://github.com/grutts/siri
Author: grutts
Author-email: git@adriang.org
License: MIT
Platform: UNKNOWN
Classifier: Development Status :: 2 - Pre-Alpha
Classifier: License :: OSI Approved :: MIT License
Classifier: Programming Language :: Python
Classifier: Programming Language :: Python :: 3
Classifier: Programming Language :: Python :: 3.6
Classifier: Programming Language :: Python :: 3.7
Classifier: Programming Language :: Python :: 3.8
Classifier: Programming Language :: Python :: 3.9
Classifier: Programming Language :: Python :: 3.10
License-File: LICENSE
Requires-Dist: xsdata (>=21.1)
